amora_py-0.2.1.dist-info/METADATA
amora_py-0.2.1.dist-info/WHEEL
amora_py-0.2.1.dist-info/license_files/LICENSE
amora_py/__init__.py
amora_py/amora_py.cpython-311-x86_64-linux-gnu.so
amora_py-0.2.1.dist-info/RECORD
