Metadata-Version: 2.1
Name: amora-py
Version: 0.2.1
Classifier: Programming Language :: Rust
Classifier: Programming Language :: Python :: Implementation :: CPython
Classifier: Programming Language :: Python :: Implementation :: PyPy
Classifier: Development Status :: 4 - Beta
Classifier: License :: OSI Approved :: Mozilla Public License 2.0 (MPL 2.0)
License-File: LICENSE
Summary: Amora is a secure token inspired by JWT and Branca, but enhanced a bit in some areas.
Keywords: token,jwt,branca,authentication,authorization
Author: Grzegorz Blach
License: MPL-2.0
Requires-Python: >=3.8
Project-URL: Repository, https://codeberg.org/gblach/amora-py
Project-URL: Issues, https://codeberg.org/gblach/amora-py/issues
